cortex_command_mod_converter_engine/__init__.py
cortex_command_mod_converter_engine/bmp_to_png.py
cortex_command_mod_converter_engine/cfg.py
cortex_command_mod_converter_engine/convert.py
cortex_command_mod_converter_engine/regex_rules.py
cortex_command_mod_converter_engine/stylua.py
cortex_command_mod_converter_engine/thumbnail_generator.py
cortex_command_mod_converter_engine/utils.py
cortex_command_mod_converter_engine/zips.py
cortex_command_mod_converter_engine/case_check/case_check.py
cortex_command_mod_converter_engine/case_check/case_check_errors.py
cortex_command_mod_converter_engine/conversion_rules/before_pre4/gibs.json
cortex_command_mod_converter_engine/conversion_rules/before_pre4/images.json
cortex_command_mod_converter_engine/conversion_rules/before_pre4/lua.json
cortex_command_mod_converter_engine/conversion_rules/before_pre4/misc.json
cortex_command_mod_converter_engine/conversion_rules/before_pre4/sounds.json
cortex_command_mod_converter_engine/conversion_rules/pre4/images.json
cortex_command_mod_converter_engine/conversion_rules/pre4/lua.json
cortex_command_mod_converter_engine/conversion_rules/pre4/misc.json
cortex_command_mod_converter_engine/conversion_rules/pre4/new_unit_names.json
cortex_command_mod_converter_engine/conversion_rules/pre4/sounds.json
cortex_command_mod_converter_engine/conversion_rules/pre5/ini.json
cortex_command_mod_converter_engine/conversion_rules/pre5/lua.json
cortex_command_mod_converter_engine/conversion_rules/pre5/sounds.json
cortex_command_mod_converter_engine/ini_converting/ini_cst.py
cortex_command_mod_converter_engine/ini_converting/ini_cst_builder.py
cortex_command_mod_converter_engine/ini_converting/ini_rules.py
cortex_command_mod_converter_engine/ini_converting/ini_rules_utils.py
cortex_command_mod_converter_engine/ini_converting/ini_tokenizer.py
cortex_command_mod_converter_engine/ini_converting/ini_writer.py
cortex_command_mod_converter_engine/stylua_executables/linux/stylua
cortex_command_mod_converter_engine-1.0.18.dist-info/METADATA
cortex_command_mod_converter_engine-1.0.18.dist-info/WHEEL
cortex_command_mod_converter_engine-1.0.18.dist-info/licenses/LICENSE
cortex_command_mod_converter_engine-1.0.18.dist-info/RECORD
