Metadata-Version: 2.1
Name: cortex-command-mod-converter-engine
Version: 1.0.18
Summary: Automatically converts mods to the latest version of the Cortex Command Community Project.
Project-URL: Homepage, https://github.com/MyNameIsTrez/Cortex-Command-Mod-Converter-Engine
Project-URL: Bug Tracker, https://github.com/MyNameIsTrez/Cortex-Command-Mod-Converter-Engine/issues
Author-email: MyNameIsTrez <welfje@gmail.com>
License-File: LICENSE
Classifier: License :: OSI Approved :: MIT License
Classifier: Operating System :: OS Independent
Classifier: Programming Language :: Python :: 3
Requires-Python: >=3.7
